simple_encoders/__init__.py
simple_encoders/base_encoder.py
simple_encoders/df_encoder.py
simple_encoders-0.1.6.dist-info/LICENSE
simple_encoders-0.1.6.dist-info/METADATA
simple_encoders-0.1.6.dist-info/WHEEL
simple_encoders-0.1.6.dist-info/top_level.txt
simple_encoders-0.1.6.dist-info/RECORD
